{
  "success": true,
  "data": {
    "borrower_loan_account_number": "IDIB3273914422",
    "address": "Iringal, Quilandy, Kozhikode District",
    "name": "Independent House in Payyoli, Payyoli",
    "application_date": "2025-09-07T18:30:00.000Z",
    "date": "2025-09-10T04:30:00.000Z",
    "time_extension": null,
    "bank_id": 6,
    "built_up_area": null,
    "total_area": null,
    "carpet_area": null,
    "super_built_up_area": null,
    "categories": "Independent House",
    "city": "Abdu Rahiman Nagar",
    "state": "Kerala",
    "location": "Payyoli",
    "estimated_discount": "20",
    "emd": 250000,
    "market_value": 3000000,
    "trending": 0,
    "private_treaty": 0,
    "id": 47755,
    "latitude": "11.545179",
    "longitude": "75.6028903",
    "min_increment": null,
    "reserve_price": 2500000,
    "description": null,
    "slug": "independent-house-in-payyoli-payyoli",
    "status": 1,
    "street_view": null,
    "property_type_id": 29,
    "location_type": "Exact",
    "possession": "Symbolic Possession",
    "borrower_name": "ANOOJA M",
    "amenities": "",
    "nearby_locations": null,
    "seo_title": "Buy Independent House in Payyoli - Best Price",
    "seo_keyword": "Independent House in Payyoli, Payyoli",
    "title_h1": "Buy Independent House in Payyoli",
    "seo_description": "Find your dream home: this independent house in Payyoli offers comfort and convenience.  It boasts ample space, modern features, and a desirable location.  Payyoli provides easy access to local amenities and attractions.  Don't miss this incredible opportunity! Call now to schedule a viewing before it's gone. This property presents exceptional value and won't last long. Secure your future today.",
    "created_at": "2025-07-31T13:30:35.000Z",
    "created_by": 1428,
    "updated_at": "2025-07-31T13:30:35.000Z",
    "modified_by": 1428,
    "created_by_name": "Automated Cataloguing",
    "modified_by_name": "Automated Cataloguing",
    "favorite": 0,
    "bank_name": "Indian Bank",
    "price_drop": 0,
    "is_price_history_consistent": true,
    "primary_photo": [
      "https://hecta-website.s3.ap-south-1.amazonaws.com/property/47755/Residential_propid_250318_IDIB3273914422_387408.jpg"
    ]
  }
}