{
  "success": true,
  "data": {
    "borrower_loan_account_number": null,
    "address": "Shop No.Ugf-16, Commercial Complex, Vibhav Khand, Gomti Nagar, Lucknow",
    "name": "Commercial Shop in Vibhav Khand, Gomti Nagar, Lucknow",
    "application_date": "2025-08-03T18:30:00.000Z",
    "date": "2025-08-04T18:30:00.000Z",
    "time_extension": null,
    "bank_id": 135,
    "built_up_area": null,
    "total_area": "27.945 Sq.mtrs",
    "carpet_area": null,
    "super_built_up_area": null,
    "categories": "Commercial Shop/Retail Space",
    "city": "Lucknow",
    "state": "Uttar Pradesh",
    "location": "Vibhav Khand",
    "estimated_discount": "20",
    "emd": 341645,
    "market_value": 4555274,
    "trending": 0,
    "private_treaty": 0,
    "id": 30436,
    "latitude": "26.8630467",
    "longitude": "81.019021",
    "min_increment": null,
    "reserve_price": 3416456,
    "description": null,
    "slug": "commercial-shop-in-vibhav-khand-gomti-nagar-lucknow",
    "status": 1,
    "street_view": null,
    "property_type_id": 16,
    "location_type": "Approximate",
    "possession": "Physical Posession",
    "borrower_name": "ISHAWASYAM COMPUTERS, CHANDRA KIRAN TIWARI, PREM CHANDER TIWARI",
    "amenities": "Close to City Mall Lucknow | Close to Wave Mall Lucknow | Near Patrakarpuram Market | Close by Laxmi market",
    "nearby_locations": null,
    "seo_title": "Commercial Shop for sale in Gomti Nagar - Best Price",
    "seo_keyword": "Commercial Shop in Vibhav Khand, Gomti Nagar, Lucknow",
    "title_h1": "Buy Commercial Shop in Vibhav Khand, Gomti Nagar, Lucknow",
    "seo_description": "Discover a prime Commercial Shop in Vibhav Khand, Gomti Nagar, Lucknow, perfect for your business needs. This property offers great potential in a bustling location. Call now to secure your investment before it's gone! Don\u2019t miss out on this opportunity.",
    "created_at": "2025-05-29T11:39:28.000Z",
    "created_by": 1428,
    "updated_at": "2025-07-14T08:51:18.000Z",
    "modified_by": 1411,
    "created_by_name": "Automated Cataloguing",
    "modified_by_name": "prajapati prasad",
    "favorite": 0,
    "bank_name": "SMFG India Credit Company",
    "price_drop": 379606,
    "is_price_history_consistent": true,
    "notice_english": [
      "Yes",
      "Yes"
    ],
    "primary_photo": [
      "https://hecta-website.s3.amazonaws.com/property/30436/1748518767852_Shop.jpg"
    ],
    "seo_image": [
      "https://hecta-website.s3.amazonaws.com/property/30436/1748518767987_Shop.jpg"
    ]
  }
}