{
  "success": true,
  "data": {
    "id": 30775,
    "borrower_name": "Ghanshyam Ashok Satale",
    "bank_name": "Tata Capital Housing Finance Limited",
    "address": "Flat No. 503, 5Th Floor, Pristine Aakanksha, Gat No.2, Bakori Road, Bakori, Near Weikfield, Pune- 412207",
    "reserve_price": 1425000,
    "dimensions": "603 Sq Ft",
    "emd": null,
    "possession": "Physical",
    "auction_date": "2024-07-26T18:30:00.000Z",
    "application_deadline": null,
    "locality": "Near Weikfield",
    "city": "Pune",
    "state": "Maharashtra",
    "pincode": null,
    "latlong": "18.593587,74.054979",
    "property_type": "Flat",
    "loan_account_number": "Tchhl0279000100071528 and Tchhl02790001000755",
    "receive_date": "2024-07-05T18:30:00.000Z",
    "bank_id": 54,
    "state_id": 14,
    "city_id": 2636,
    "property_type_id": null,
    "created_at": "2024-08-06T05:49:01.000Z",
    "created_by": null,
    "extra_details": null,
    "ao_name": null,
    "ao_mobile": null,
    "ao_email": null,
    "favorite": 0
  }
}