{
  "success": true,
  "data": {
    "id": 70923,
    "borrower_name": "RAMALINGAM SUNDARESA DESIKAR",
    "bank_name": "Axis Bank",
    "address": "All that piece and parcel of the land situated at Old No 180, New No. 135, Mathur Village, Sriperampudur Taluk, Kancheepuram District comprised in S Nos",
    "reserve_price": 1864013,
    "dimensions": "293.5sq.ft",
    "emd": null,
    "possession": "Physical",
    "auction_date": "2024-12-18T18:30:00.000Z",
    "application_deadline": "2024-12-16T18:30:00.000Z",
    "locality": "sriperumbudur",
    "city": "Sriperumbudur",
    "state": "TAMIL NADU",
    "pincode": null,
    "latlong": null,
    "property_type": null,
    "loan_account_number": null,
    "receive_date": "2024-11-17T18:30:00.000Z",
    "bank_id": 13,
    "state_id": 23,
    "city_id": 3357,
    "property_type_id": null,
    "created_at": "2024-11-19T09:43:48.000Z",
    "created_by": null,
    "extra_details": null,
    "ao_name": null,
    "ao_mobile": null,
    "ao_email": null,
    "favorite": 0
  }
}