{
  "success": true,
  "data": {
    "id": 70755,
    "borrower_name": "B  HARESH",
    "bank_name": "Axis Bank",
    "address": "Plot No.2 part, Gramani Street, Irandam Kattalai Village, Kundrathur, Kancheepuram",
    "reserve_price": 1295325,
    "dimensions": "606 Sq.ft",
    "emd": null,
    "possession": "Physical",
    "auction_date": "2024-12-11T18:30:00.000Z",
    "application_deadline": "2024-12-09T18:30:00.000Z",
    "locality": "KANYAKUMARI",
    "city": "Kanniyakumari",
    "state": "TAMIL NADU",
    "pincode": null,
    "latlong": null,
    "property_type": "Residential Plot",
    "loan_account_number": null,
    "receive_date": "2024-11-17T18:30:00.000Z",
    "bank_id": 13,
    "state_id": 23,
    "city_id": 3693,
    "property_type_id": 2,
    "created_at": "2024-11-19T09:43:48.000Z",
    "created_by": null,
    "extra_details": null,
    "ao_name": null,
    "ao_mobile": null,
    "ao_email": null,
    "favorite": 0
  }
}