{
  "success": true,
  "data": {
    "id": 71021,
    "borrower_name": "BRIJESH KUMAR",
    "bank_name": "Axis Bank",
    "address": "RESIDENTIAL PROPERTY BEING ON REVENUE SURVEY NO 731, SUB PLOT NO 115, 116/A, MAIN PLOT NO 115 AND 116, MARUTI NAGAR- 3, SUB DIST ANJAR, DIST KUTCH",
    "reserve_price": 565600,
    "dimensions": "56.00 SQ MTS",
    "emd": null,
    "possession": "Physical",
    "auction_date": "2024-12-18T18:30:00.000Z",
    "application_deadline": "2024-12-16T18:30:00.000Z",
    "locality": "ANJAR",
    "city": "Anjar",
    "state": "GUJARAT",
    "pincode": null,
    "latlong": null,
    "property_type": "Residential Plot",
    "loan_account_number": null,
    "receive_date": "2024-11-17T18:30:00.000Z",
    "bank_id": 13,
    "state_id": 7,
    "city_id": 952,
    "property_type_id": 2,
    "created_at": "2024-11-19T09:43:48.000Z",
    "created_by": null,
    "extra_details": null,
    "ao_name": null,
    "ao_mobile": null,
    "ao_email": null,
    "favorite": 0
  }
}